ngl_resum/__init__.py
ngl_resum/ngl_resum.py
ngl_resum-0.1.0.dist-info/LICENSE
ngl_resum-0.1.0.dist-info/METADATA
ngl_resum-0.1.0.dist-info/WHEEL
ngl_resum-0.1.0.dist-info/top_level.txt
ngl_resum-0.1.0.dist-info/RECORD
