Metadata-Version: 2.1
Name: ngl-resum
Version: 0.1.0
Summary: Resummation of non-global logarithms at leading logarithmic accuracy
Home-page: https://github.com/MarcelBalsiger/ngl_resum
Author: Marcel Balsiger
Author-email: marcel.balsiger@hotmail.com
License: UNKNOWN
Platform: UNKNOWN
Classifier: Programming Language :: Python :: 3
Classifier: License :: OSI Approved :: MIT License
Classifier: Operating System :: OS Independent
Requires-Python: >=3.6
Requires-Dist: numpy
Requires-Dist: physt
Requires-Dist: pylhe
